datasets/__init__.py
datasets/funcLib/Ackley.py
datasets/funcLib/Beale.py
datasets/funcLib/Booth.py
datasets/funcLib/Bukin.py
datasets/funcLib/Camel.py
datasets/funcLib/DeJongF3.py
datasets/funcLib/Easom.py
datasets/funcLib/Eggholder.py
datasets/funcLib/Ellipsoid.py
datasets/funcLib/FiveWell.py
datasets/funcLib/G1.py
datasets/funcLib/Goldstain.py
datasets/funcLib/Griewank.py
datasets/funcLib/Ktable.py
datasets/funcLib/Levi.py
datasets/funcLib/Matyas.py
datasets/funcLib/McCormick.py
datasets/funcLib/Michalewicz.py
datasets/funcLib/Rastrigin.py
datasets/funcLib/Rosenbrock.py
datasets/funcLib/Schaffer2.py
datasets/funcLib/Schaffer4.py
datasets/funcLib/Schwefel.py
datasets/funcLib/Shuberts.py
datasets/funcLib/SixHump.py
datasets/funcLib/Sphere.py
datasets/funcLib/SumDiffPower.py
datasets/funcLib/WeightedSphere.py
datasets/funcLib/XinShe.py
datasets/funcLib/Zahkarov.py
datasets/funcLib/__init__.py
flopt/__init__.py
flopt/apis.py
flopt/constants.py
flopt/constraint.py
flopt/container.py
flopt/env.py
flopt/error.py
flopt/expression.py
flopt/flopt.config
flopt/polynomial.py
flopt/problem.py
flopt/solution.py
flopt/utils.py
flopt/variable.py
flopt/convert/__init__.py
flopt/convert/_pulp.py
flopt/convert/binarize.py
flopt/convert/linearize.py
flopt/convert/structure.py
flopt/performance/__init__.py
flopt/performance/base_dataset.py
flopt/performance/custom_dataset.py
flopt/performance/func_dataset.py
flopt/performance/log_visualizer.py
flopt/performance/mip_dataset.py
flopt/performance/performance.py
flopt/performance/tsp_dataset.py
flopt/solvers/__init__.py
flopt/solvers/amplify_search.py
flopt/solvers/auto_search.py
flopt/solvers/base.py
flopt/solvers/cvxopt_search.py
flopt/solvers/hyperopt_search.py
flopt/solvers/optuna_searches.py
flopt/solvers/pulp_search.py
flopt/solvers/random_search.py
flopt/solvers/selector.py
flopt/solvers/shuffled_frog_leaping_search.py
flopt/solvers/steepest_descent.py
flopt/solvers/two_opt.py
flopt/solvers/scipy_searches/__init__.py
flopt-0.5.6.dist-info/LICENSE
flopt-0.5.6.dist-info/METADATA
flopt-0.5.6.dist-info/WHEEL
flopt-0.5.6.dist-info/top_level.txt
flopt-0.5.6.dist-info/RECORD
