Metadata-Version: 2.1
Name: flopt
Version: 0.5.6
Summary: A python Non-Linear Programming API with Heuristic approach
Home-page: https://flopt.readthedocs.io/en/latest/index.html
Author: nariaki tateiwa
Author-email: nariaki3551@gmail.com
License: MIT
Keywords: optimization nonliear search heuristics algorithm
Platform: UNKNOWN
Classifier: License :: OSI Approved :: MIT License
Classifier: Programming Language :: Python :: 3.9
Classifier: Programming Language :: Python :: 3.10
License-File: LICENSE
Requires-Dist: numpy
Requires-Dist: sympy
Requires-Dist: matplotlib
Requires-Dist: pulp
Requires-Dist: optuna
Requires-Dist: hyperopt
Requires-Dist: cvxopt
Requires-Dist: amplify
Requires-Dist: pytest
Requires-Dist: scipy
Requires-Dist: scikit-learn
Requires-Dist: dill
Requires-Dist: pooch
Requires-Dist: timeout-decorator
Requires-Dist: colorlog
